fragment/__init__.py
fragment/codegen/__init__.py
fragment/codegen/__main__.py
fragment/codegen/generator.py
fragment/entry.py
fragment/math_parser.py
fragment/schema_parser.py
fragment/types.py
fragment/utils.py
fragment_py-0.1.1.dist-info/METADATA
fragment_py-0.1.1.dist-info/WHEEL
fragment_py-0.1.1.dist-info/entry_points.txt
fragment_py-0.1.1.dist-info/RECORD
