Metadata-Version: 2.1
Name: fragment-py
Version: 0.1.1
Summary: Python SDK for working with the Fragment API
Author: Vignesh
Author-email: vignesh@fragment.dev
Requires-Python: >=3.10.13,<4.0.0
Classifier: Programming Language :: Python :: 3
Classifier: Programming Language :: Python :: 3.11
Classifier: Programming Language :: Python :: 3.12
Requires-Dist: rich (>=13.7.0,<14.0.0)
Requires-Dist: strenum (>=0.4.15,<0.5.0)
Requires-Dist: typer (>=0.9.0,<0.10.0)
